[
  {
    "tag": "Generic-PUMP-001",
    "name": "Horizontal Centrifugal Pump",
    "componentClass": "Pump",
    "dexpiType": "CentrifugalPump",
    "rdlUri": "http://posccaesar.org/rdl/RDS288594",
    "description": "Single-stage, overhung, horizontally mounted centrifugal pump for process water.",
    "operatingConditions": {
      "pressureMax": {
        "value": 20,
        "unit": "bar",
        "source": "API 610"
      },
      "pressureMin": {
        "value": 1,
        "unit": "bar"
      },
      "pressureDesign": {
        "value": 16,
        "unit": "bar"
      },
      "pressureOperating": {
        "value": 10,
        "unit": "bar"
      },
      "temperatureMax": {
        "value": 120,
        "unit": "C"
      },
      "temperatureMin": {
        "value": -10,
        "unit": "C"
      },
      "temperatureDesign": {
        "value": 100,
        "unit": "C"
      },
      "temperatureOperating": {
        "value": 80,
        "unit": "C"
      },
      "flowRateDesign": {
        "value": 150,
        "unit": "m3/h"
      },
      "flowRateOperating": {
        "value": 120,
        "unit": "m3/h"
      }
    },
    "specifications": {
      "power": {
        "value": 45,
        "unit": "kW",
        "source": "IEC 60034"
      },
      "rotationalSpeed": {
        "value": 2950,
        "unit": "rpm"
      },
      "efficiency": {
        "value": 75,
        "unit": "%"
      },
      "head": {
        "value": 60,
        "unit": "m"
      },
      "NPSHr": {
        "value": 3.5,
        "unit": "m"
      },
      "dutyPoint": {
        "value": "Continuous",
        "unit": ""
      }
    },
    "design": {
      "weight": {
        "value": 450,
        "unit": "kg"
      },
      "length": {
        "value": 1200,
        "unit": "mm"
      },
      "width": {
        "value": 600,
        "unit": "mm"
      },
      "height": {
        "value": 800,
        "unit": "mm"
      }
    },
    "materials": {
      "casing": "ASTM A216 WCB",
      "impeller": "ASTM A743 CA6NM",
      "shaft": "AISI 4140",
      "seals": "Tungsten Carbide / Silicon Carbide",
      "gaskets": "PTFE",
      "bolting": "ASTM A193 B7",
      "baseplate": "ASTM A36"
    },
    "nozzles": [
      {
        "id": "N1",
        "name": "Suction",
        "service": "Process Inlet",
        "size": "DN150",
        "rating": "PN16",
        "facing": "RF",
        "position": "End"
      },
      {
        "id": "N2",
        "name": "Discharge",
        "service": "Process Outlet",
        "size": "DN100",
        "rating": "PN40",
        "facing": "RF",
        "position": "Top"
      },
      {
        "id": "N3",
        "name": "Drain",
        "service": "Drain",
        "size": "DN25",
        "rating": "PN16",
        "facing": "RF",
        "position": "Bottom"
      },
      {
        "id": "N4",
        "name": "Vent",
        "service": "Vent",
        "size": "DN25",
        "rating": "PN16",
        "facing": "RF",
        "position": "Top"
      }
    ],
    "standards": [
      "API 610",
      "ASME B73.1",
      "ISO 5199",
      "IEC 60034"
    ],
    "image_prompt": "Highly detailed 3D rendering of a horizontal centrifugal pump on a steel baseplate, painted industrial blue, showing suction and discharge flanges."
  },
  {
    "tag": "Generic-VALVE-001",
    "name": "Wedge Gate Valve",
    "componentClass": "Valve",
    "dexpiType": "GateValve",
    "rdlUri": "http://posccaesar.org/rdl/RDS321456",
    "description": "Flanged end, outside screw and yoke (OS&Y), bolted bonnet, rising stem wedge gate valve for isolation.",
    "operatingConditions": {
      "pressureMax": {
        "value": 50,
        "unit": "bar",
        "source": "ASME B16.34"
      },
      "pressureMin": {
        "value": 0,
        "unit": "bar"
      },
      "pressureDesign": {
        "value": 40,
        "unit": "bar"
      },
      "pressureOperating": {
        "value": 25,
        "unit": "bar"
      },
      "temperatureMax": {
        "value": 400,
        "unit": "C"
      },
      "temperatureMin": {
        "value": -29,
        "unit": "C"
      },
      "temperatureDesign": {
        "value": 350,
        "unit": "C"
      },
      "temperatureOperating": {
        "value": 200,
        "unit": "C"
      },
      "flowRateDesign": {
        "value": 500,
        "unit": "m3/h"
      },
      "flowRateOperating": {
        "value": 450,
        "unit": "m3/h"
      }
    },
    "specifications": {
      "power": {
        "value": 0,
        "unit": "kW",
        "source": "N/A"
      },
      "rotationalSpeed": {
        "value": 0,
        "unit": "rpm"
      },
      "efficiency": {
        "value": 100,
        "unit": "%"
      },
      "head": {
        "value": 0,
        "unit": "m"
      },
      "NPSHr": {
        "value": 0,
        "unit": "m"
      },
      "dutyPoint": {
        "value": "Intermittent",
        "unit": ""
      }
    },
    "design": {
      "weight": {
        "value": 180,
        "unit": "kg"
      },
      "length": {
        "value": 356,
        "unit": "mm"
      },
      "width": {
        "value": 350,
        "unit": "mm"
      },
      "height": {
        "value": 850,
        "unit": "mm"
      }
    },
    "materials": {
      "casing": "ASTM A216 WCB",
      "impeller": "N/A",
      "shaft": "ASTM A182 F6a",
      "seals": "Graphite",
      "gaskets": "Spiral Wound SS316/Graphite",
      "bolting": "ASTM A193 B7",
      "baseplate": "N/A"
    },
    "nozzles": [
      {
        "id": "N1",
        "name": "Inlet",
        "service": "Process Inlet",
        "size": "DN150",
        "rating": "Class 300",
        "facing": "RF",
        "position": "Side"
      },
      {
        "id": "N2",
        "name": "Outlet",
        "service": "Process Outlet",
        "size": "DN150",
        "rating": "Class 300",
        "facing": "RF",
        "position": "Side"
      }
    ],
    "standards": [
      "API 600",
      "ASME B16.34",
      "ASME B16.5"
    ],
    "image_prompt": "Industrial wedge gate valve with handwheel, painted silver, flanged connections, set against a white background."
  },
  {
    "tag": "Generic-HEX-001",
    "name": "Shell and Tube Heat Exchanger",
    "componentClass": "HeatExchanger",
    "dexpiType": "ShellAndTubeHeatExchanger",
    "rdlUri": "http://posccaesar.org/rdl/RDS987654",
    "description": "TEMA Type BEM shell and tube heat exchanger for fluid cooling.",
    "operatingConditions": {
      "pressureMax": {
        "value": 30,
        "unit": "bar",
        "source": "ASME BPVC VIII"
      },
      "pressureMin": {
        "value": 1,
        "unit": "bar"
      },
      "pressureDesign": {
        "value": 25,
        "unit": "bar"
      },
      "pressureOperating": {
        "value": 18,
        "unit": "bar"
      },
      "temperatureMax": {
        "value": 250,
        "unit": "C"
      },
      "temperatureMin": {
        "value": -10,
        "unit": "C"
      },
      "temperatureDesign": {
        "value": 200,
        "unit": "C"
      },
      "temperatureOperating": {
        "value": 150,
        "unit": "C"
      },
      "flowRateDesign": {
        "value": 300,
        "unit": "m3/h"
      },
      "flowRateOperating": {
        "value": 250,
        "unit": "m3/h"
      }
    },
    "specifications": {
      "power": {
        "value": 0,
        "unit": "kW",
        "source": "N/A"
      },
      "rotationalSpeed": {
        "value": 0,
        "unit": "rpm"
      },
      "efficiency": {
        "value": 85,
        "unit": "%"
      },
      "head": {
        "value": 0,
        "unit": "m"
      },
      "NPSHr": {
        "value": 0,
        "unit": "m"
      },
      "dutyPoint": {
        "value": "Continuous",
        "unit": ""
      }
    },
    "design": {
      "weight": {
        "value": 4500,
        "unit": "kg"
      },
      "length": {
        "value": 4000,
        "unit": "mm"
      },
      "width": {
        "value": 1000,
        "unit": "mm"
      },
      "height": {
        "value": 1200,
        "unit": "mm"
      }
    },
    "materials": {
      "casing": "ASTM A516 Gr 70",
      "impeller": "N/A",
      "shaft": "N/A",
      "seals": "N/A",
      "gaskets": "Spiral Wound SS316",
      "bolting": "ASTM A193 B7",
      "baseplate": "ASTM A36"
    },
    "nozzles": [
      {
        "id": "N1",
        "name": "Shell Inlet",
        "service": "Hot Fluid In",
        "size": "DN200",
        "rating": "PN16",
        "facing": "RF",
        "position": "Top"
      },
      {
        "id": "N2",
        "name": "Shell Outlet",
        "service": "Hot Fluid Out",
        "size": "DN200",
        "rating": "PN16",
        "facing": "RF",
        "position": "Bottom"
      },
      {
        "id": "N3",
        "name": "Tube Inlet",
        "service": "Cold Fluid In",
        "size": "DN150",
        "rating": "PN16",
        "facing": "RF",
        "position": "Channel Bottom"
      },
      {
        "id": "N4",
        "name": "Tube Outlet",
        "service": "Cold Fluid Out",
        "size": "DN150",
        "rating": "PN16",
        "facing": "RF",
        "position": "Channel Top"
      }
    ],
    "standards": [
      "TEMA",
      "ASME BPVC VIII Div 1",
      "API 660"
    ],
    "image_prompt": "Detailed 3D model of a horizontal shell and tube heat exchanger, steel body, visible flanged nozzles."
  }
]