[
  {
    "vendor": "Flowserve",
    "model": "HPX API 610 OH2",
    "referenceId": "P-101A",
    "description": "The Flowserve HPX is a premium API 610 (OH2) single-stage, overhung, radially split, process pump designed for the oil and gas and hydrocarbon processing industries.",
    "differentiators": [
      "API 610 12th Edition Compliant",
      "Optimized hydraulics for wide operating range",
      "Robust bearing housing design for extended life"
    ],
    "specifications": {
      "type": "Centrifugal OH2",
      "maxFlow": "3000 m3/h",
      "maxHead": "350 m",
      "maxTemperature": "450 C"
    },
    "documents": [
      {
        "title": "HPX Datasheet",
        "url": "https://www.flowserve.com/en/products/pumps/overhung/hpx/"
      },
      {
        "title": "User Manual",
        "url": "https://www.flowserve.com/en/resources/manuals/"
      }
    ]
  },
  {
    "vendor": "ITT Goulds Pumps",
    "model": "Model 3700 API 610 OH2",
    "referenceId": "P-101A",
    "description": "The Model 3700 is an API 610 12th Edition compliant, overhung, process pump for high temperature and high pressure applications.",
    "differentiators": [
      "Heavy duty shaft and bearing system",
      "Finned bearing frame for enhanced cooling",
      "Condition monitoring ready"
    ],
    "specifications": {
      "type": "Centrifugal OH2",
      "maxFlow": "1930 m3/h",
      "maxHead": "360 m",
      "maxTemperature": "425 C"
    },
    "documents": [
      {
        "title": "Model 3700 Product Brochure",
        "url": "https://www.gouldspumps.com/Products/API-Process-Pumps/Model-3700/"
      },
      {
        "title": "IOM Manual",
        "url": "https://www.gouldspumps.com/en-US/Support/Document-Library/"
      }
    ]
  },
  {
    "vendor": "Sulzer",
    "model": "OHL API 610 OH2",
    "referenceId": "P-101A",
    "description": "Sulzer OHL pumps are single-stage, overhung, radially split centrifugal process pumps designed according to API 610 standards.",
    "differentiators": [
      "High-efficiency enclosed impeller",
      "Broad hydraulic coverage",
      "Centerline mounted for thermal stability"
    ],
    "specifications": {
      "type": "Centrifugal OH2",
      "maxFlow": "2500 m3/h",
      "maxHead": "380 m",
      "maxTemperature": "450 C"
    },
    "documents": [
      {
        "title": "OHL Product Page",
        "url": "https://www.sulzer.com/en/products/pumps/centrifugal-pumps/api-610-pumps/ohl-api-610-oh2-process-pump"
      },
      {
        "title": "Technical Datasheet",
        "url": "https://www.sulzer.com/en/shared/documents/"
      }
    ]
  }
]
