[
  {
    "vendor": "Siemens",
    "model": "SIMOTICS SD 1LE5",
    "referenceId": "P-101-MOTOR",
    "description": "Low-voltage AC motor with high efficiency and rugged cast-iron housing designed for heavy duty and severe industrial environments.",
    "differentiators": [
      "NEMA Premium Efficiency",
      "Severe Duty Cast-Iron Frame",
      "Inverter Duty Rated"
    ],
    "specifications": {
      "horsepower": "50 HP",
      "poles": "4-pole",
      "voltage": "460 V",
      "enclosure": "TEFC",
      "frame": "326T"
    },
    "documents": [
      {
        "title": "Datasheet",
        "url": "https://www.todaycomponents.com/pub/media/datasheet/1LE22214DA113AA3.pdf"
      }
    ]
  },
  {
    "vendor": "ABB",
    "model": "Process Performance IE4",
    "referenceId": "P-101-MOTOR",
    "description": "Cast iron induction motor designed for maximum reliability and efficiency in continuous process industries.",
    "differentiators": [
      "IE4 Super Premium Efficiency",
      "Robust Cast Iron Construction",
      "Low Vibration and Noise"
    ],
    "specifications": {
      "efficiencyClass": "IE4",
      "material": "Cast Iron",
      "protection": "IP55",
      "cooling": "IC411"
    },
    "documents": [
      {
        "title": "Datasheet",
        "url": "https://search.abb.com/library/Download.aspx?DocumentID=9AKK107424&LanguageCode=en&DocumentPartId=&Action=Launch"
      }
    ]
  },
  {
    "vendor": "WEG",
    "model": "W22 Three-Phase",
    "referenceId": "P-101-MOTOR",
    "description": "High efficiency three-phase electric motor with an advanced aerodynamic frame design for improved heat dissipation.",
    "differentiators": [
      "Optimized Cooling System",
      "High Grade Cast Iron Frame",
      "Class F Insulation"
    ],
    "specifications": {
      "insulation": "Class F",
      "voltage": "230/460 V",
      "frequency": "50/60 Hz",
      "enclosure": "TEFC"
    },
    "documents": [
      {
        "title": "Brochure",
        "url": "https://static.weg.net/medias/downloadcenter/h52/h99/WEG-w22-single-phase-european-market-50069268-brochure-english-web.pdf"
      }
    ]
  }
]